 <ns5:SubmitObjectsRequest xmlns:xsi="http://www.w3.org/2001/XMLSchema-instance" xmlns:xsd="http://www.w3.org/2001/XMLSchema" xmlns:ns5="urn:oasis:names:tc:ebxml-regrep:xsd:lcm:3.0">
     <RegistryObjectList xmlns="urn:oasis:names:tc:ebxml-regrep:xsd:rim:3.0">
         <!--##################################################################-->
         <!--RegistryPackage-->
         <!--##################################################################-->
         <ns2:RegistryPackage  xmlns:ns2="urn:oasis:names:tc:ebxml-regrep:xsd:rim:3.0" id="urn:uuid:92900cbc-e0c5-42bc-8723-f4b1dab721c6"  status="urn:oasis:names:tc:ebxml-regrep:StatusType:Approved"  >
             <!--===================-->
             <!--SubmissionTime-->
             <!--===================-->
             <ns2:Slot name="submissionTime"> 
                 <ns2:ValueList>
                     <ns2:Value>20230731102803</ns2:Value>
                 </ns2:ValueList>
             </ns2:Slot>
             <!--===================-->
             <!--Name-->
             <!--===================-->
             <ns2:Name>
                 <ns2:LocalizedString xml:lang="FR" charset="UTF8" value="Compte rendu d'examens biologiques"/>
             </ns2:Name>
             <!--===================-->
             <!--Description (comments)-->
             <!--===================-->
             <ns2:Description>
                 <ns2:LocalizedString xml:lang="FR" charset="UTF8" value=""/>
             </ns2:Description>
             <!--===================-->
             <!--Classification-->
             <!--===================-->
             <ns2:Classification id = "SubmissionSet01_c001"
             classificationNode = "urn:uuid:a54d6aa5-d40d-43f9-88c5-b4633d873bdd"	classifiedObject = "urn:uuid:92900cbc-e0c5-42bc-8723-f4b1dab721c6" nodeRepresentation = "" />
             <!--===================-->
             <!--Author attributes-->
             <!--===================-->
             <ns2:Classification id="urn:uuid:e64ac63e-51ec-43fc-929e-576ffa75a51f" classificationScheme="urn:uuid:a7058bb9-b4e4-4307-ba5b-e3f0ab85e12d" classifiedObject="urn:uuid:92900cbc-e0c5-42bc-8723-f4b1dab721c6" nodeRepresentation=""> 
             <!--===================-->
             <!--AuthorInstitution-->
             <!--===================-->
                 <ns2:Slot name="authorInstitution">
                     <ns2:ValueList>
                         <ns2:Value>Laboratoire des charmes^^^^^&amp;1.2.250.1.71.4.2.2&amp;ISO^IDNST^^^1120459876</ns2:Value>
                     </ns2:ValueList>
                 </ns2:Slot>
             <!--===================-->
             <!--AuthorPerson-->
             <!--===================-->
             <ns2:Slot name="authorPerson">
                 <ns2:ValueList>
                 <ns2:Value>801234534765^CAMPARINI^Marcel^^^^^^&amp;1.2.250.1.71.4.2.1&amp;ISO^D^^^IDNPS</ns2:Value>
                 </ns2:ValueList>
             </ns2:Slot>
             <!--===================-->
             <!--AuthorSpecialty-->
             <!--===================-->
             <ns2:Slot name="authorSpecialty">
                 <ns2:ValueList>
                     <ns2:Value>G15_10/SM03^Médecin - Biologie médicale (SM)^1.2.250.1.213.1.1.4.5</ns2:Value>
                 </ns2:ValueList>
             </ns2:Slot>
             </ns2:Classification>
             <!--===================-->
             <!--HealthcareFacility-->
             <!--===================-->
             <ns2:Classification id="SubmissionSet01_c002" classificationScheme="urn:uuid:aa543740-bdda-424e-8c96-df4873be8500" classifiedObject="urn:uuid:92900cbc-e0c5-42bc-8723-f4b1dab721c6" nodeRepresentation="SA25" >
                 <ns2:Slot name="codingScheme" >
                     <ns2:ValueList>
                         <ns2:Value>1.2.250.1.71.4.2.4</ns2:Value>
                     </ns2:ValueList>
                 </ns2:Slot>
                 <ns2:Name>
                     <ns2:LocalizedString xml:lang="FR" charset="UTF8" value="Laboratoire de biologie médicale"/>	
                 </ns2:Name>
             </ns2:Classification>
             <!--===================-->
             <!--PatientId-->
             <!--===================-->
             <ns2:ExternalIdentifier id="urn:uuid:ee6f654f-f997-4434-bc72-4438a32017d0" identificationScheme="urn:uuid:6b5aea1a-874d-4603-a4bc-96a0a7b38446" registryObject="urn:uuid:a6e06ca8-0c75-4064-9e5d-88b9045a9ab6" value="277076322082910^^^&amp;1.2.250.1.213.1.4.8&amp;ISO^NH">
                 <ns2:Name>
                     <ns2:LocalizedString value="XDSSubmissionSet.patientId"/>
                 </ns2:Name>
             </ns2:ExternalIdentifier>
             <!--===================-->
             <!--SourceId-->
             <!--===================-->
             <ns2:ExternalIdentifier id="urn:uuid:00c0c3e1-85ce-4d20-b3fb-6d8ff3d0f700" identificationScheme="urn:uuid:554ac39e-e3fe-47fe-b233-965d2a147832" registryObject="urn:uuid:a6e06ca8-0c75-4064-9e5d-88b9045a9ab6" value="1.2.250.1.71.4.2.2.1120459876">
                 <ns2:Name>
                     <ns2:LocalizedString value="XDSSumissionSet.sourceId"/>
                 </ns2:Name>
             </ns2:ExternalIdentifier>
             <!--===================-->
             <!--UniqueId-->
             <!--===================-->
             <ns2:ExternalIdentifier id="urn:uuid:4479e344-8f39-4cbd-b1d2-606e66a43e4d" identificationScheme="urn:uuid:96fdda7c-d067-4183-912e-bf5ee74998a8" registryObject="urn:uuid:a6e06ca8-0c75-4064-9e5d-88b9045a9ab6" value="1.2.250.1.213.1.1.1.1.2023.7.7.638263960831146701">
                 <ns2:Name>
                     <ns2:LocalizedString value="XDSSubmissionSet.uniqueId"/>
                 </ns2:Name>
             </ns2:ExternalIdentifier>
         </ns2:RegistryPackage>
         <!-- ################################################################## -->
         <!--   Extrinsic object - CDA DOC0001.XML-->
         <!-- ################################################################## -->
         <ns2:ExtrinsicObject mimeType="text/xml" objectType="urn:uuid:7edca82f-054d-47f2-a032-9b2a5b5186c1" id="urn:uuid:urn:uuid:951efe44-40b4-44f8-9731-173fa042f502" xmlns:ns2="urn:oasis:names:tc:ebxml-regrep:xsd:rim:3.0" status="urn:oasis:names:tc:ebxml-regrep:StatusType:Approved"	>
             <!--===================-->
             <!--Hash-->
             <!--===================-->
             <ns2:Slot name="hash">
                 <ns2:ValueList>
                     <ns2:Value>D76E0EA875C78206C0AF10A53EDAA428F789182A</ns2:Value>
                 </ns2:ValueList>
             </ns2:Slot>
             <!--===================-->
             <!--Size-->
             <!--===================-->
             <ns2:Slot name="size">
                 <ns2:ValueList>
                     <ns2:Value>160709</ns2:Value>
                 </ns2:ValueList>
             </ns2:Slot>
             <!--===================-->
             <!--URI-->
             <!--===================-->
             <ns2:Slot name="URI">
                 <ns2:ValueList>
                     <ns2:Value>DOC0001.XML</ns2:Value>
                 </ns2:ValueList>
             </ns2:Slot>
             <!--===================-->
             <!--CreationTime-->
             <!--===================-->
             <ns2:Slot name="creationTime">
                 <ns2:ValueList>
                     <ns2:Value>20210104150527</ns2:Value>
                 </ns2:ValueList>
             </ns2:Slot>
             <!--===================-->
             <!--LangageCode-->
             <!--===================-->
             <ns2:Slot name="languageCode">
                 <ns2:ValueList>
                     <ns2:Value>fr-FR</ns2:Value>
                 </ns2:ValueList>
             </ns2:Slot>
             <!--===================-->
             <!--LegalAuthenticator-->
             <!--===================-->
             <ns2:Slot name="legalAuthenticator">
                 <ns2:ValueList>
                     <ns2:Value>801234534765^CAMPARINI^Marcel^^^^^^&amp;1.2.250.1.71.4.2.1&amp;ISO^D^^^IDNPS</ns2:Value>
                 </ns2:ValueList>
             </ns2:Slot>
             <!--===================-->
             <!--ServiceStartTime-->
             <!--===================-->
             <ns2:Slot name="serviceStartTime">
                 <ns2:ValueList>
                     <ns2:Value>20210104082200</ns2:Value>
                 </ns2:ValueList>
             </ns2:Slot>
             <!--===================-->
             <!--ServiceStopTime-->
             <!--===================-->
             <ns2:Slot name="serviceStopTime">
                 <ns2:ValueList>
                     <ns2:Value>20210104150500</ns2:Value>
                 </ns2:ValueList>
             </ns2:Slot>
             <!--===================-->
             <!--SourcePatientId-->
             <!--===================-->
             <ns2:Slot name="sourcePatientId">
                 <ns2:ValueList>
                     <ns2:Value>1234567890121^^^&amp;1.2.3.4.567.8.9.10&amp;ISO^PI</ns2:Value>
                 </ns2:ValueList>
             </ns2:Slot>
             <!--===================-->
             <!--SourcePatientInfo-->
             <!--===================-->
             <ns2:Slot name="sourcePatientInfo">
                 <ns2:ValueList>
                     <ns2:Value>PID-5|NESSI^Ruth Isabelle^^^^^L</ns2:Value>
                     <ns2:Value>PID-5|DECOURCY^Ruth^^^^^D</ns2:Value>
                     <ns2:Value>PID-7|19770714</ns2:Value>
                     <ns2:Value>PID-8|F</ns2:Value>
                 </ns2:ValueList>
             </ns2:Slot>
             <!--===================-->
             <!--Name-->
             <!--===================-->
             <ns2:Name>
                 <ns2:LocalizedString xml:lang="FR" charset="UTF8"                  value="Compte rendu d'examens biologiques"/>
             </ns2:Name>
             <!--===================-->
             <!--Description (Comments)-->
             <!--===================-->
             <ns2:Description>
                 <ns2:LocalizedString xml:lang="FR" charset="UTF8"                  value=""/>
             </ns2:Description>
             <!--===================-->
             <!--EventCodeList-->
             <!--===================-->
             <ns2:Classification classificationScheme="urn:uuid:2c6b8cb7-8b2a-4051-b291-b1ae6a575ef4" classifiedObject="urn:uuid:urn:uuid:951efe44-40b4-44f8-9731-173fa042f502" id="urn:uuid:885a358c-5ea8-44a7-8c61-abf0599846a1"               nodeRepresentation="18719-5" objectType="urn:oasis:names:tc:ebxml-regrep:ObjectType:RegistryObject:Classification" >
                 <ns2:Slot name="codingScheme">
                     <ns2:ValueList>
                         <ns2:Value>2.16.840.1.113883.6.1</ns2:Value>
                     </ns2:ValueList>
                 </ns2:Slot>
                 <ns2:Name>
                     <ns2:LocalizedString xml:lang="FR" charset="UTF8"                      value="Biochimie"/>
                 </ns2:Name>
             </ns2:Classification>
             <ns2:Classification classificationScheme="urn:uuid:2c6b8cb7-8b2a-4051-b291-b1ae6a575ef4" classifiedObject="urn:uuid:urn:uuid:951efe44-40b4-44f8-9731-173fa042f502" id="urn:uuid:d7faa117-85fd-4d39-bbbb-7531103e1554"               nodeRepresentation="18723-7" objectType="urn:oasis:names:tc:ebxml-regrep:ObjectType:RegistryObject:Classification" >
                 <ns2:Slot name="codingScheme">
                     <ns2:ValueList>
                         <ns2:Value>2.16.840.1.113883.6.1</ns2:Value>
                     </ns2:ValueList>
                 </ns2:Slot>
                 <ns2:Name>
                     <ns2:LocalizedString xml:lang="FR" charset="UTF8"                      value="Hématologie"/>
                 </ns2:Name>
             </ns2:Classification>
             <ns2:Classification classificationScheme="urn:uuid:2c6b8cb7-8b2a-4051-b291-b1ae6a575ef4" classifiedObject="urn:uuid:urn:uuid:951efe44-40b4-44f8-9731-173fa042f502" id="urn:uuid:7ec33cb6-16c9-4a22-ba26-5f1cadd79034"               nodeRepresentation="18725-2" objectType="urn:oasis:names:tc:ebxml-regrep:ObjectType:RegistryObject:Classification" >
                 <ns2:Slot name="codingScheme">
                     <ns2:ValueList>
                         <ns2:Value>2.16.840.1.113883.6.1</ns2:Value>
                     </ns2:ValueList>
                 </ns2:Slot>
                 <ns2:Name>
                     <ns2:LocalizedString xml:lang="FR" charset="UTF8"                      value="Microbiologie"/>
                 </ns2:Name>
             </ns2:Classification>
             <!--*********************************************************-->
             <!--  Authors Attributes -->
             <!--*********************************************************-->
             <ns2:Classification id="urn:uuid:5ca79268-ef97-4dbe-b809-d4dafe4de9bf" classificationScheme="urn:uuid:93606bcf-9494-43ec-9b4e-a7748d1a838d" classifiedObject="urn:uuid:92900cbc-e0c5-42bc-8723-f4b1dab721c6" nodeRepresentation=""> 
                 <!--===================-->
                 <!--AuthorInstitution-->
                 <!--===================-->
                 <ns2:Slot name="authorInstitution">
                     <ns2:ValueList>
                         <ns2:Value>Laboratoire des charmes^^^^^&amp;1.2.250.1.71.4.2.2&amp;ISO^IDNST^^^1120459876</ns2:Value>
                     </ns2:ValueList>
                 </ns2:Slot>
                 <!--===================-->
                 <!--AuthorPerson-->
                 <!--===================-->
                 <ns2:Slot name="authorPerson">
                     <ns2:ValueList>
                     <ns2:Value>801234534765^CAMPARINI^Marcel^^^^^^&amp;1.2.250.1.71.4.2.1&amp;ISO^D^^^IDNPS</ns2:Value>
                     </ns2:ValueList>
                 </ns2:Slot>
                 <!--===================-->
                 <!--AuthorSpecialty-->
                 <!--===================-->
                 <ns2:Slot name="authorSpecialty">
                     <ns2:ValueList>
                         <ns2:Value>G15_10/SM03^Médecin - Biologie médicale (SM)^1.2.250.1.213.1.1.4.5</ns2:Value>
                     </ns2:ValueList>
                 </ns2:Slot>
                 </ns2:Classification>
                 <!--*********************************************************-->
                 <!--  Class -->
                 <!--*********************************************************-->
                 <!--  -->
                 <ns2:Classification id="urn:uuid:959b2445-d6c7-4b00-b23f-bee8f7cd2b86" classificationScheme="urn:uuid:41a5887f-8865-4c09-adf7-e362475b143a" classifiedObject="urn:uuid:92900cbc-e0c5-42bc-8723-f4b1dab721c6" nodeRepresentation="10">
                     <ns2:Slot name="codingScheme">
                         <ns2:ValueList>
                             <ns2:Value>1.2.250.1.213.1.1.4.1</ns2:Value>
                         </ns2:ValueList>
                     </ns2:Slot>
                     <ns2:Name>
                         <ns2:LocalizedString value="Compte rendu"/>
                     </ns2:Name>
                 </ns2:Classification>
                 <!-- ***************************************************************************-->
                 <!--     Confidentiality  -->
                 <!-- ***************************************************************************-->
                 <ns2:Classification id="urn:uuid:8199cf7b-d634-4055-80cb-ad4d680e20b2" classificationScheme="urn:uuid:f4f85eac-e6cb-4883-b524-f2705394840f" classifiedObject="urn:uuid:92900cbc-e0c5-42bc-8723-f4b1dab721c6" nodeRepresentation="N">
                     <ns2:Slot name="codingScheme">
                         <ns2:ValueList>
                             <ns2:Value>2.16.840.1.113883.5.25</ns2:Value>
                         </ns2:ValueList>
                     </ns2:Slot>
                     <ns2:Name>
                         <ns2:LocalizedString value="Normal"/>
                     </ns2:Name>
                 </ns2:Classification>
                 <!--***********************************-->
                 <!--  Format -->
                 <!--***********************************-->
                 <ns2:Classification id="urn:uuid:c24f86f1-cbe0-4f64-bbd4-3cc6a5750f93" classificationScheme="urn:uuid:a09d5840-386c-46f2-b5ad-9c3699a4309d" classifiedObject="urn:uuid:92900cbc-e0c5-42bc-8723-f4b1dab721c6" nodeRepresentation="urn:ihe:lab:xd-lab:2008"> 
                     <ns2:Slot name="codingScheme">
                         <ns2:ValueList>
                             <ns2:Value>2.16.840.1.113883.6.1</ns2:Value>
                         </ns2:ValueList>
                     </ns2:Slot>
                     <ns2:Name>
                         <ns2:LocalizedString value="Compte rendu structuré d'examens de biologie médicale"/>
                     </ns2:Name>
                 </ns2:Classification>
                 <!--***********************************-->
                 <!--  HealthcareFacility -->
                 <!--***********************************-->
                 <ns2:Classification id="urn:uuid:18e675e8-3ec6-451e-b989-71543f110462" classificationScheme="urn:uuid:f33fb8ac-18af-42cc-ae0e-ed0b0bdb91e1" classifiedObject="urn:uuid:92900cbc-e0c5-42bc-8723-f4b1dab721c6" nodeRepresentation="SA25">
                     <ns2:Slot name="codingScheme">
                         <ns2:ValueList>
                             <ns2:Value>1.2.250.1.71.4.2.4</ns2:Value>
                         </ns2:ValueList>
                     </ns2:Slot>
                     <ns2:Name>
                         <ns2:LocalizedString value="Laboratoire de biologie médicale"/>
                     </ns2:Name>
                 </ns2:Classification>
                 <!--********************************-->
                 <!--  Practice Settings -->
                 <!--********************************-->
                 <ns2:Classification id="urn:uuid:a330813d-b9ad-4dc6-8831-0df34561f984" classificationScheme="urn:uuid:cccf5598-8b07-4b77-a05e-ae952c785ead" classifiedObject="urn:uuid:92900cbc-e0c5-42bc-8723-f4b1dab721c6" nodeRepresentation="AMBULATOIRE">
                     <ns2:Slot name="codingScheme">
                         <ns2:ValueList>
                             <ns2:Value>1.2.250.1.213.1.1.4.9</ns2:Value>
                         </ns2:ValueList>
                     </ns2:Slot>
                     <ns2:Name>
                         <ns2:LocalizedString  xml:lang="FR" charset="UTF8"  value="Ambulatoire"   />
                     </ns2:Name>
                 </ns2:Classification>
                 <!--********************************-->
                 <!--  Type -->
                 <!--********************************-->
                 <ns2:Classification id="urn:uuid:397077cb-34dc-40c9-8548-c44ebd396188" classificationScheme="urn:uuid:f0306f51-975f-434e-a61c-c59651d33983" classifiedObject="urn:uuid:92900cbc-e0c5-42bc-8723-f4b1dab721c6" nodeRepresentation="11502-2">
                     <ns2:Slot name="codingScheme">
                         <ns2:ValueList>
                             <ns2:Value>2.16.840.1.113883.6.1</ns2:Value>
                         </ns2:ValueList>
                     </ns2:Slot>
                     <ns2:Name>
                         <ns2:LocalizedString  xml:lang="FR" charset="UTF8"  value="CR d'examens biologiques"   />
                     </ns2:Name>
                 </ns2:Classification>
                 <!--********************************-->
                 <!--  PatientId -->
                 <!--********************************-->
                 <ns2:ExternalIdentifier id="urn:uuid:99f1f0c2-5929-4fb5-b6e3-d8d18efd7049" identificationScheme="urn:uuid:58a6f841-87b3-4a3e-92fd-a8ffeff98427" registryObject="urn:uuid:4a889fd4-012f-4000-e008-12c48372fe64" value="277076322082910^^^&amp;1.2.250.1.213.1.4.8&amp;ISO^NH">
                     <ns2:Name>
                         <ns2:LocalizedString value="XDSDocumentEntry.patientId"/>
                     </ns2:Name>
                 </ns2:ExternalIdentifier>
                 <!--********************************-->
                 <!--  UniqueId -->
                 <!--********************************-->
                 <ns2:ExternalIdentifier id="urn:uuid:7cc5a1a5-1845-45e5-84cc-0771afb35e50" identificationScheme="urn:uuid:2e82c1f6-a085-4c72-9da3-8640a32e42ab" registryObject="b576aac4-33be-4875-b875-f8ee50bf66e0" value="1.3.6.1.4.1.19376.1.3.3.4">
                     <ns2:Name>
                         <ns2:LocalizedString xml:lang="FR" charset="UTF8"  value="XDSDocumentEntry.uniqueId"/>
                     </ns2:Name>
                 </ns2:ExternalIdentifier>
             </ns2:ExtrinsicObject>
             <!--*****************************************-->
             <!--*            ASSOCIATIONS -->
             <!--*****************************************-->
             <ns2:Association id="urn:uuid:1b58b4a4-57fd-4fbe-bcbf-ca2901f2c187" objectType="Original" associationType="urn:oasis:names:tc:ebxml-regrep:AssociationType:HasMember"               sourceObject="urn:uuid:92900cbc-e0c5-42bc-8723-f4b1dab721c6" targetObject="urn:uuid:urn:uuid:951efe44-40b4-44f8-9731-173fa042f502"  xmlns:ns2="urn:oasis:names:tc:ebxml-regrep:xsd:rim:3.0"  >
                 <ns2:Slot name="SubmissionSetStatus">
                     <ns2:ValueList>
                         <ns2:Value>Original</ns2:Value>
                     </ns2:ValueList>
                 </ns2:Slot>
             </ns2:Association>
     </RegistryObjectList>
 </ns5:SubmitObjectsRequest>

